Metadata-Version: 2.1
Name: odoo9-addon-web-listview-custom-element-number
Version: 9.0.1.0.0.99.dev6
Summary: Allow users to set manually a quantity of items to display in a tree view
Home-page: https://odoo-community.org/
Author: GRAP,Akretion,Odoo Community Association (OCA)
Author-email: support@odoo-community.org
License: AGPL-3
Platform: UNKNOWN
Classifier: Programming Language :: Python
Classifier: Framework :: Odoo
Classifier: License :: OSI Approved :: GNU Affero General Public License v3
Requires-Python: ~=2.7
Requires-Dist: odoo (<9.1a,>=9.0a)
